datamart.py
datamart-2021.3.17.dist-info/LICENSE.txt
datamart-2021.3.17.dist-info/METADATA
datamart-2021.3.17.dist-info/NOTICE.txt
datamart-2021.3.17.dist-info/WHEEL
datamart-2021.3.17.dist-info/top_level.txt
datamart-2021.3.17.dist-info/RECORD
