Metadata-Version: 2.1
Name: datamart
Version: 2021.3.17
Summary: Datamart API
Home-page: https://gitlab.com/ViDA-NYU/datamart/datamart
Author: DARPA Datamart Program
Maintainer: Remi Rampin
Maintainer-email: remi.rampin@nyu.edu
License: Apache-2.0
Project-URL: Homepage, https://gitlab.com/datadrivendiscovery/datamart-api
Project-URL: Source, https://gitlab.com/datadrivendiscovery/datamart-api
Project-URL: Tracker, https://gitlab.com/datadrivendiscovery/datamart-api/issues
Keywords: datamart,d3m
Platform: UNKNOWN
Classifier: Development Status :: 3 - Alpha
Classifier: Intended Audience :: Science/Research
Classifier: License :: OSI Approved :: Apache Software License
Classifier: Natural Language :: English
Classifier: Operating System :: OS Independent
Classifier: Programming Language :: Python :: 3
Classifier: Topic :: Scientific/Engineering :: Information Analysis
Requires-Dist: d3m
